[
    {
        "name": "double ema",
        "className": "DoubleMaStrategy",
        "vtSymbol": "XBTUSD.TESTBITMEX"
    },

    {
        "name": "atr rsi",
        "className": "AtrRsiStrategy",
        "vtSymbol": "XBTUSD.TESTBITMEX"
    },

    {
        "name": "king keltner",
        "className": "KkStrategy",
        "vtSymbol": "XBTUSD.TESTBITMEX"
    },
        {
        "name": "test strategy",
        "className": "TestStrategy",
        "vtSymbol": "XBTUSD.TESTBITMEX"
    },
        {
        "name": "Turtle strategy",
        "className": "TurtleTradingStrategy",
        "vtSymbol": "XBTUSD.TESTBITMEX"
    }

]